bulbasaur/__init__.py
bulbasaur/converters.py
bulbasaur/errors.py
bulbasaur/type_mappings.py
bulbasaur-0.2.0.dist-info/licenses/LICENSE
bulbasaur-0.2.0.dist-info/METADATA
bulbasaur-0.2.0.dist-info/WHEEL
bulbasaur-0.2.0.dist-info/top_level.txt
bulbasaur-0.2.0.dist-info/RECORD
